README.rst
setup.py
seccs/__init__.py
seccs/crypto_wrapper.py
seccs/rc.py
seccs/test.py
seccs.egg-info/PKG-INFO
seccs.egg-info/SOURCES.txt
seccs.egg-info/dependency_links.txt
seccs.egg-info/requires.txt
seccs.egg-info/top_level.txt