Metadata-Version: 1.1
Name: seccs
Version: 0.0.5
Summary: Secure Content Store
Home-page: https://github.com/netleibi/seccs
Author: Dominik Leibenger
Author-email: python-seccs@mails.dominik-leibenger.de
License: Apache Software License
Platform: UNKNOWN
Classifier: Development Status :: 2 - Pre-Alpha
Classifier: Intended Audience :: Developers
Classifier: Topic :: Software Development :: Libraries :: Python Modules
Classifier: License :: OSI Approved :: Apache Software License
Classifier: Operating System :: OS Independent
Classifier: Programming Language :: Python :: 3
Classifier: Programming Language :: Python :: 3.5
